crams_allocation/__init__.py
crams_allocation/admin.py
crams_allocation/apps.py
crams_allocation/asgi.py
crams_allocation/models.py
crams_allocation/permissions.py
crams_allocation/settings.py
crams_allocation/test_utils.py
crams_allocation/urls.py
crams_allocation/wsgi.py
crams_allocation/config/__init__.py
crams_allocation/config/allocation_config.py
crams_allocation/config/aspect_config.py
crams_allocation/config/transaction_id.py
crams_allocation/constants/__init__.py
crams_allocation/constants/api.py
crams_allocation/constants/db.py
crams_allocation/constants/db_qs.py
crams_allocation/local/__init__.py
crams_allocation/log/__init__.py
crams_allocation/log/allocation_request_log.py
crams_allocation/log/provision_log.py
crams_allocation/migrations/0001_initial.py
crams_allocation/migrations/0002_init_lookups.py
crams_allocation/migrations/0003_notificationtemplate_contact_license_status.py
crams_allocation/migrations/__init__.py
crams_allocation/product_allocation/__init__.py
crams_allocation/product_allocation/models.py
crams_allocation/product_allocation/serializers/__init__.py
crams_allocation/product_allocation/serializers/compute_question_serializer.py
crams_allocation/product_allocation/serializers/compute_request.py
crams_allocation/product_allocation/serializers/storage_question_serializers.py
crams_allocation/product_allocation/serializers/storage_request_serializers.py
crams_allocation/serializers/__init__.py
crams_allocation/serializers/admin_serializers.py
crams_allocation/serializers/base.py
crams_allocation/serializers/base_lookup.py
crams_allocation/serializers/contact_project_list.py
crams_allocation/serializers/product_request.py
crams_allocation/serializers/project_list.py
crams_allocation/serializers/project_request_serializers.py
crams_allocation/serializers/question_serializers.py
crams_allocation/serializers/request_history.py
crams_allocation/serializers/request_serializers.py
crams_allocation/sqls/initial_allocation.sql
crams_allocation-1.0.2.dist-info/METADATA
crams_allocation-1.0.2.dist-info/WHEEL
crams_allocation-1.0.2.dist-info/top_level.txt
crams_allocation-1.0.2.dist-info/RECORD
